{"instrument_id": "j1805", "date_time": "20180412 15:00:00", "high": 1781.0, "low": 1781.0, "close": 1781.0, "open": 1781.0}
{"instrument_id": "j1805", "date_time": "20180413 18:35:16", "high": 1781.0, "low": 1781.0, "close": 1781.0, "open": 1781.0}
{"instrument_id": "j1805", "date_time": "20180413 20:59:00", "high": 1789.5, "low": 1789.5, "close": 1789.5, "open": 1789.5}
{"instrument_id": "j1805", "date_time": "20180413 21:00:00", "high": 1785.5, "low": 1780.0, "close": 1783.5, "open": 1782.0}
{"instrument_id": "j1805", "date_time": "20180413 21:01:00", "high": 1787.5, "low": 1779.5, "close": 1787.5, "open": 1784.0}
{"instrument_id": "j1805", "date_time": "20180413 21:02:00", "high": 1787.0, "low": 1782.0, "close": 1784.5, "open": 1787.0}
{"instrument_id": "j1805", "date_time": "20180413 21:03:00", "high": 1789.0, "low": 1784.0, "close": 1788.0, "open": 1785.0}
{"instrument_id": "j1805", "date_time": "20180413 21:04:00", "high": 1789.0, "low": 1786.0, "close": 1788.5, "open": 1787.5}
{"instrument_id": "j1805", "date_time": "20180413 21:05:00", "high": 1790.0, "low": 1787.5, "close": 1790.0, "open": 1788.5}
{"instrument_id": "j1805", "date_time": "20180413 21:06:00", "high": 1790.0, "low": 1787.0, "close": 1788.0, "open": 1789.5}
{"instrument_id": "j1805", "date_time": "20180413 21:07:00", "high": 1788.0, "low": 1781.5, "close": 1783.5, "open": 1788.0}
{"instrument_id": "j1805", "date_time": "20180413 21:08:01", "high": 1785.0, "low": 1783.5, "close": 1785.0, "open": 1783.5}
{"instrument_id": "j1805", "date_time": "20180413 21:09:03", "high": 1785.0, "low": 1783.0, "close": 1783.0, "open": 1785.0}
{"instrument_id": "j1805", "date_time": "20180413 21:10:00", "high": 1784.5, "low": 1782.5, "close": 1784.5, "open": 1783.0}
{"instrument_id": "j1805", "date_time": "20180413 21:11:01", "high": 1784.5, "low": 1783.0, "close": 1783.0, "open": 1784.5}
{"instrument_id": "j1805", "date_time": "20180413 21:12:00", "high": 1784.5, "low": 1782.0, "close": 1783.5, "open": 1783.0}
{"instrument_id": "j1805", "date_time": "20180413 21:13:00", "high": 1786.5, "low": 1783.5, "close": 1786.5, "open": 1784.5}
{"instrument_id": "j1805", "date_time": "20180413 21:14:00", "high": 1786.5, "low": 1785.5, "close": 1786.0, "open": 1786.0}
{"instrument_id": "j1805", "date_time": "20180413 21:15:00", "high": 1786.0, "low": 1784.0, "close": 1784.5, "open": 1786.0}
{"instrument_id": "j1805", "date_time": "20180413 21:16:00", "high": 1785.5, "low": 1784.0, "close": 1784.5, "open": 1784.5}
{"instrument_id": "j1805", "date_time": "20180413 21:17:04", "high": 1786.0, "low": 1784.0, "close": 1784.0, "open": 1784.5}
{"instrument_id": "j1805", "date_time": "20180413 21:18:00", "high": 1786.0, "low": 1782.5, "close": 1785.0, "open": 1784.0}
{"instrument_id": "j1805", "date_time": "20180413 21:19:00", "high": 1787.0, "low": 1785.0, "close": 1786.0, "open": 1785.0}
{"instrument_id": "j1805", "date_time": "20180413 21:20:00", "high": 1787.0, "low": 1783.0, "close": 1784.0, "open": 1786.0}
{"instrument_id": "j1805", "date_time": "20180413 21:21:00", "high": 1785.5, "low": 1783.5, "close": 1785.0, "open": 1784.0}
{"instrument_id": "j1805", "date_time": "20180413 21:22:01", "high": 1786.0, "low": 1785.0, "close": 1785.0, "open": 1785.0}
{"instrument_id": "j1805", "date_time": "20180413 21:23:00", "high": 1787.0, "low": 1785.0, "close": 1785.0, "open": 1785.0}
{"instrument_id": "j1805", "date_time": "20180413 21:24:00", "high": 1785.0, "low": 1784.0, "close": 1784.0, "open": 1785.0}
{"instrument_id": "j1805", "date_time": "20180413 21:25:01", "high": 1784.5, "low": 1782.0, "close": 1782.0, "open": 1784.5}
{"instrument_id": "j1805", "date_time": "20180413 21:26:00", "high": 1785.5, "low": 1781.5, "close": 1785.0, "open": 1782.0}
{"instrument_id": "j1805", "date_time": "20180413 21:27:02", "high": 1786.5, "low": 1784.0, "close": 1784.5, "open": 1785.0}
{"instrument_id": "j1805", "date_time": "20180413 21:28:02", "high": 1786.5, "low": 1782.5, "close": 1786.5, "open": 1784.5}
{"instrument_id": "j1805", "date_time": "20180413 21:29:00", "high": 1786.5, "low": 1782.0, "close": 1782.5, "open": 1786.5}
{"instrument_id": "j1805", "date_time": "20180413 21:30:00", "high": 1784.5, "low": 1781.0, "close": 1783.5, "open": 1782.5}
{"instrument_id": "j1805", "date_time": "20180413 21:31:00", "high": 1786.5, "low": 1783.5, "close": 1786.0, "open": 1783.5}
{"instrument_id": "j1805", "date_time": "20180413 21:32:00", "high": 1786.0, "low": 1784.0, "close": 1784.5, "open": 1786.0}
{"instrument_id": "j1805", "date_time": "20180413 21:33:02", "high": 1785.0, "low": 1783.0, "close": 1784.5, "open": 1784.0}
{"instrument_id": "j1805", "date_time": "20180413 21:34:00", "high": 1785.0, "low": 1783.5, "close": 1785.0, "open": 1784.5}
{"instrument_id": "j1805", "date_time": "20180413 21:35:00", "high": 1785.5, "low": 1783.5, "close": 1784.5, "open": 1785.0}
{"instrument_id": "j1805", "date_time": "20180413 21:36:04", "high": 1786.0, "low": 1784.5, "close": 1785.5, "open": 1784.5}
{"instrument_id": "j1805", "date_time": "20180413 21:37:02", "high": 1785.5, "low": 1783.5, "close": 1785.0, "open": 1785.5}
{"instrument_id": "j1805", "date_time": "20180413 21:38:07", "high": 1785.0, "low": 1783.0, "close": 1784.0, "open": 1785.0}
{"instrument_id": "j1805", "date_time": "20180413 21:39:00", "high": 1784.5, "low": 1783.0, "close": 1783.5, "open": 1784.0}
{"instrument_id": "j1805", "date_time": "20180413 21:40:03", "high": 1783.5, "low": 1782.5, "close": 1783.0, "open": 1783.0}
{"instrument_id": "j1805", "date_time": "20180413 21:41:00", "high": 1783.5, "low": 1782.5, "close": 1783.5, "open": 1782.5}
{"instrument_id": "j1805", "date_time": "20180413 21:42:05", "high": 1784.0, "low": 1782.5, "close": 1783.0, "open": 1783.5}
{"instrument_id": "j1805", "date_time": "20180413 21:43:00", "high": 1783.0, "low": 1781.0, "close": 1781.0, "open": 1782.5}
{"instrument_id": "j1805", "date_time": "20180413 21:44:02", "high": 1782.0, "low": 1781.0, "close": 1781.0, "open": 1781.0}
{"instrument_id": "j1805", "date_time": "20180413 21:45:01", "high": 1783.0, "low": 1781.0, "close": 1782.0, "open": 1781.0}
{"instrument_id": "j1805", "date_time": "20180413 21:46:00", "high": 1783.5, "low": 1782.0, "close": 1783.5, "open": 1782.0}
{"instrument_id": "j1805", "date_time": "20180413 21:47:06", "high": 1784.5, "low": 1783.5, "close": 1783.5, "open": 1783.5}
{"instrument_id": "j1805", "date_time": "20180413 21:48:02", "high": 1783.5, "low": 1783.0, "close": 1783.5, "open": 1783.5}
{"instrument_id": "j1805", "date_time": "20180413 21:49:01", "high": 1785.0, "low": 1783.0, "close": 1783.5, "open": 1784.0}
{"instrument_id": "j1805", "date_time": "20180413 21:50:00", "high": 1784.5, "low": 1783.0, "close": 1784.5, "open": 1783.0}
{"instrument_id": "j1805", "date_time": "20180413 21:51:00", "high": 1784.5, "low": 1782.5, "close": 1784.5, "open": 1784.5}
{"instrument_id": "j1805", "date_time": "20180413 21:52:00", "high": 1784.5, "low": 1783.5, "close": 1784.0, "open": 1784.5}
{"instrument_id": "j1805", "date_time": "20180413 21:53:01", "high": 1785.0, "low": 1784.0, "close": 1784.5, "open": 1784.0}
{"instrument_id": "j1805", "date_time": "20180413 21:54:02", "high": 1785.0, "low": 1784.5, "close": 1784.5, "open": 1784.5}
{"instrument_id": "j1805", "date_time": "20180413 21:55:04", "high": 1784.5, "low": 1784.0, "close": 1784.0, "open": 1784.5}
{"instrument_id": "j1805", "date_time": "20180413 21:56:05", "high": 1786.0, "low": 1784.0, "close": 1786.0, "open": 1784.0}
{"instrument_id": "j1805", "date_time": "20180413 21:57:05", "high": 1786.0, "low": 1783.0, "close": 1783.5, "open": 1786.0}
{"instrument_id": "j1805", "date_time": "20180413 21:58:00", "high": 1784.0, "low": 1783.0, "close": 1784.0, "open": 1783.5}
{"instrument_id": "j1805", "date_time": "20180413 21:59:00", "high": 1784.5, "low": 1783.5, "close": 1784.0, "open": 1784.0}
{"instrument_id": "j1805", "date_time": "20180413 22:00:01", "high": 1784.5, "low": 1783.0, "close": 1784.5, "open": 1783.5}
{"instrument_id": "j1805", "date_time": "20180413 22:01:00", "high": 1785.0, "low": 1784.5, "close": 1785.0, "open": 1784.5}
{"instrument_id": "j1805", "date_time": "20180413 22:02:00", "high": 1785.5, "low": 1784.5, "close": 1784.5, "open": 1785.0}
{"instrument_id": "j1805", "date_time": "20180413 22:03:01", "high": 1784.5, "low": 1784.0, "close": 1784.0, "open": 1784.5}
{"instrument_id": "j1805", "date_time": "20180413 22:04:06", "high": 1784.5, "low": 1784.0, "close": 1784.0, "open": 1784.0}
{"instrument_id": "j1805", "date_time": "20180413 22:05:16", "high": 1784.0, "low": 1784.0, "close": 1784.0, "open": 1784.0}
{"instrument_id": "j1805", "date_time": "20180413 22:06:00", "high": 1785.0, "low": 1784.0, "close": 1784.0, "open": 1784.0}
{"instrument_id": "j1805", "date_time": "20180413 22:07:02", "high": 1785.0, "low": 1784.0, "close": 1784.5, "open": 1784.0}
{"instrument_id": "j1805", "date_time": "20180413 22:08:00", "high": 1787.5, "low": 1784.5, "close": 1786.0, "open": 1784.5}
{"instrument_id": "j1805", "date_time": "20180413 22:09:00", "high": 1787.5, "low": 1786.0, "close": 1786.5, "open": 1786.5}
{"instrument_id": "j1805", "date_time": "20180413 22:10:00", "high": 1786.5, "low": 1785.5, "close": 1785.5, "open": 1786.5}
{"instrument_id": "j1805", "date_time": "20180413 22:11:08", "high": 1786.0, "low": 1785.5, "close": 1785.5, "open": 1785.5}
{"instrument_id": "j1805", "date_time": "20180413 22:12:07", "high": 1786.5, "low": 1785.5, "close": 1786.5, "open": 1785.5}
{"instrument_id": "j1805", "date_time": "20180413 22:13:02", "high": 1786.5, "low": 1785.5, "close": 1785.5, "open": 1786.5}
{"instrument_id": "j1805", "date_time": "20180413 22:14:04", "high": 1786.0, "low": 1784.5, "close": 1785.0, "open": 1784.5}
{"instrument_id": "j1805", "date_time": "20180413 22:15:00", "high": 1785.0, "low": 1784.0, "close": 1785.0, "open": 1785.0}
{"instrument_id": "j1805", "date_time": "20180413 22:16:00", "high": 1787.0, "low": 1785.0, "close": 1786.0, "open": 1785.0}
{"instrument_id": "j1805", "date_time": "20180413 22:17:00", "high": 1786.0, "low": 1785.0, "close": 1785.5, "open": 1786.0}
{"instrument_id": "j1805", "date_time": "20180413 22:18:00", "high": 1786.0, "low": 1785.0, "close": 1786.0, "open": 1785.5}
{"instrument_id": "j1805", "date_time": "20180413 22:19:00", "high": 1786.5, "low": 1785.0, "close": 1785.0, "open": 1786.0}
{"instrument_id": "j1805", "date_time": "20180413 22:20:00", "high": 1786.0, "low": 1785.0, "close": 1785.5, "open": 1785.0}
{"instrument_id": "j1805", "date_time": "20180413 22:21:00", "high": 1786.0, "low": 1785.5, "close": 1785.5, "open": 1785.5}
{"instrument_id": "j1805", "date_time": "20180413 22:22:07", "high": 1786.0, "low": 1785.5, "close": 1785.5, "open": 1785.5}
{"instrument_id": "j1805", "date_time": "20180413 22:23:01", "high": 1786.0, "low": 1784.0, "close": 1784.0, "open": 1785.5}
{"instrument_id": "j1805", "date_time": "20180413 22:24:01", "high": 1784.0, "low": 1782.5, "close": 1783.5, "open": 1784.0}
{"instrument_id": "j1805", "date_time": "20180413 22:25:00", "high": 1785.0, "low": 1783.0, "close": 1785.0, "open": 1783.5}
{"instrument_id": "j1805", "date_time": "20180413 22:26:01", "high": 1787.5, "low": 1784.5, "close": 1786.5, "open": 1785.0}
{"instrument_id": "j1805", "date_time": "20180413 22:27:00", "high": 1787.0, "low": 1785.0, "close": 1786.5, "open": 1786.5}
{"instrument_id": "j1805", "date_time": "20180413 22:28:00", "high": 1786.0, "low": 1784.0, "close": 1785.5, "open": 1786.0}
{"instrument_id": "j1805", "date_time": "20180413 22:29:06", "high": 1785.5, "low": 1784.0, "close": 1785.0, "open": 1785.5}
{"instrument_id": "j1805", "date_time": "20180413 22:30:00", "high": 1785.0, "low": 1783.5, "close": 1785.0, "open": 1785.0}
{"instrument_id": "j1805", "date_time": "20180413 22:31:01", "high": 1785.0, "low": 1784.0, "close": 1784.0, "open": 1785.0}
{"instrument_id": "j1805", "date_time": "20180413 22:32:00", "high": 1784.5, "low": 1784.0, "close": 1784.0, "open": 1784.0}
{"instrument_id": "j1805", "date_time": "20180413 22:33:00", "high": 1785.0, "low": 1784.0, "close": 1785.0, "open": 1784.0}
{"instrument_id": "j1805", "date_time": "20180413 22:34:00", "high": 1785.0, "low": 1784.0, "close": 1784.5, "open": 1785.0}
{"instrument_id": "j1805", "date_time": "20180413 22:35:02", "high": 1784.5, "low": 1784.0, "close": 1784.5, "open": 1784.5}
{"instrument_id": "j1805", "date_time": "20180413 22:36:02", "high": 1784.5, "low": 1783.5, "close": 1783.5, "open": 1784.5}
{"instrument_id": "j1805", "date_time": "20180413 22:37:00", "high": 1784.0, "low": 1783.0, "close": 1784.0, "open": 1783.5}
{"instrument_id": "j1805", "date_time": "20180413 22:38:01", "high": 1785.0, "low": 1784.0, "close": 1785.0, "open": 1784.0}
{"instrument_id": "j1805", "date_time": "20180413 22:39:00", "high": 1785.0, "low": 1785.0, "close": 1785.0, "open": 1785.0}
{"instrument_id": "j1805", "date_time": "20180413 22:40:04", "high": 1785.0, "low": 1783.5, "close": 1783.5, "open": 1785.0}
{"instrument_id": "j1805", "date_time": "20180413 22:41:00", "high": 1784.0, "low": 1783.5, "close": 1783.5, "open": 1783.5}
{"instrument_id": "j1805", "date_time": "20180413 22:42:08", "high": 1785.0, "low": 1783.5, "close": 1784.5, "open": 1783.5}
{"instrument_id": "j1805", "date_time": "20180413 22:43:14", "high": 1784.5, "low": 1783.5, "close": 1783.5, "open": 1784.5}
{"instrument_id": "j1805", "date_time": "20180413 22:44:02", "high": 1784.0, "low": 1782.0, "close": 1784.0, "open": 1783.5}
{"instrument_id": "j1805", "date_time": "20180413 22:45:00", "high": 1785.0, "low": 1783.5, "close": 1784.0, "open": 1784.0}
{"instrument_id": "j1805", "date_time": "20180413 22:46:03", "high": 1785.0, "low": 1784.0, "close": 1784.5, "open": 1784.0}
{"instrument_id": "j1805", "date_time": "20180413 22:47:02", "high": 1784.5, "low": 1784.5, "close": 1784.5, "open": 1784.5}
{"instrument_id": "j1805", "date_time": "20180413 22:48:05", "high": 1784.5, "low": 1784.5, "close": 1784.5, "open": 1784.5}
{"instrument_id": "j1805", "date_time": "20180413 22:49:04", "high": 1784.5, "low": 1783.5, "close": 1784.0, "open": 1784.5}
{"instrument_id": "j1805", "date_time": "20180413 22:50:00", "high": 1785.0, "low": 1784.0, "close": 1785.0, "open": 1784.0}
{"instrument_id": "j1805", "date_time": "20180413 22:51:02", "high": 1785.5, "low": 1784.5, "close": 1785.0, "open": 1784.5}
{"instrument_id": "j1805", "date_time": "20180413 22:52:02", "high": 1785.0, "low": 1783.5, "close": 1784.0, "open": 1784.5}
{"instrument_id": "j1805", "date_time": "20180413 22:53:02", "high": 1785.0, "low": 1784.0, "close": 1784.0, "open": 1784.0}
{"instrument_id": "j1805", "date_time": "20180413 22:54:00", "high": 1784.5, "low": 1784.0, "close": 1784.5, "open": 1784.0}
{"instrument_id": "j1805", "date_time": "20180413 22:55:01", "high": 1784.5, "low": 1784.0, "close": 1784.5, "open": 1784.5}
{"instrument_id": "j1805", "date_time": "20180413 22:56:02", "high": 1784.5, "low": 1784.5, "close": 1784.5, "open": 1784.5}
{"instrument_id": "j1805", "date_time": "20180413 22:57:13", "high": 1784.5, "low": 1783.5, "close": 1783.5, "open": 1784.5}
{"instrument_id": "j1805", "date_time": "20180413 22:58:00", "high": 1784.0, "low": 1783.5, "close": 1784.0, "open": 1783.5}
{"instrument_id": "j1805", "date_time": "20180413 22:59:00", "high": 1784.0, "low": 1783.5, "close": 1783.5, "open": 1784.0}
{"instrument_id": "j1805", "date_time": "20180413 23:00:01", "high": 1784.5, "low": 1783.5, "close": 1784.0, "open": 1783.5}
{"instrument_id": "j1805", "date_time": "20180413 23:01:04", "high": 1784.0, "low": 1783.0, "close": 1783.0, "open": 1784.0}
{"instrument_id": "j1805", "date_time": "20180413 23:02:00", "high": 1783.5, "low": 1782.0, "close": 1782.5, "open": 1782.5}
{"instrument_id": "j1805", "date_time": "20180413 23:03:00", "high": 1783.5, "low": 1782.5, "close": 1782.5, "open": 1782.5}
{"instrument_id": "j1805", "date_time": "20180413 23:04:02", "high": 1783.5, "low": 1782.0, "close": 1782.0, "open": 1782.5}
{"instrument_id": "j1805", "date_time": "20180413 23:05:11", "high": 1783.5, "low": 1782.0, "close": 1783.5, "open": 1782.0}
{"instrument_id": "j1805", "date_time": "20180413 23:06:02", "high": 1784.0, "low": 1783.0, "close": 1783.0, "open": 1783.5}
{"instrument_id": "j1805", "date_time": "20180413 23:07:02", "high": 1783.0, "low": 1782.5, "close": 1782.5, "open": 1783.0}
{"instrument_id": "j1805", "date_time": "20180413 23:08:04", "high": 1782.5, "low": 1782.0, "close": 1782.0, "open": 1782.5}
{"instrument_id": "j1805", "date_time": "20180413 23:09:01", "high": 1782.5, "low": 1782.5, "close": 1782.5, "open": 1782.5}
{"instrument_id": "j1805", "date_time": "20180413 23:10:00", "high": 1782.5, "low": 1780.5, "close": 1781.0, "open": 1782.5}
{"instrument_id": "j1805", "date_time": "20180413 23:11:00", "high": 1781.0, "low": 1777.0, "close": 1778.5, "open": 1781.0}
{"instrument_id": "j1805", "date_time": "20180413 23:12:03", "high": 1778.5, "low": 1776.5, "close": 1776.5, "open": 1778.5}
{"instrument_id": "j1805", "date_time": "20180413 23:13:00", "high": 1779.0, "low": 1776.5, "close": 1778.0, "open": 1776.5}
{"instrument_id": "j1805", "date_time": "20180413 23:14:01", "high": 1778.5, "low": 1777.5, "close": 1777.5, "open": 1778.0}
{"instrument_id": "j1805", "date_time": "20180413 23:15:04", "high": 1778.5, "low": 1776.0, "close": 1778.0, "open": 1777.5}
{"instrument_id": "j1805", "date_time": "20180413 23:16:04", "high": 1778.5, "low": 1777.5, "close": 1778.0, "open": 1778.0}
{"instrument_id": "j1805", "date_time": "20180413 23:17:00", "high": 1778.0, "low": 1776.0, "close": 1776.0, "open": 1778.0}
{"instrument_id": "j1805", "date_time": "20180413 23:18:00", "high": 1781.0, "low": 1776.0, "close": 1778.0, "open": 1776.5}
{"instrument_id": "j1805", "date_time": "20180413 23:19:00", "high": 1778.0, "low": 1776.5, "close": 1777.5, "open": 1778.0}
{"instrument_id": "j1805", "date_time": "20180413 23:20:00", "high": 1778.0, "low": 1777.0, "close": 1778.0, "open": 1777.5}
{"instrument_id": "j1805", "date_time": "20180413 23:21:02", "high": 1778.5, "low": 1778.0, "close": 1778.5, "open": 1778.0}
{"instrument_id": "j1805", "date_time": "20180413 23:22:00", "high": 1778.5, "low": 1777.5, "close": 1778.0, "open": 1778.0}
{"instrument_id": "j1805", "date_time": "20180413 23:23:08", "high": 1780.0, "low": 1778.0, "close": 1779.0, "open": 1778.0}
{"instrument_id": "j1805", "date_time": "20180413 23:24:05", "high": 1780.0, "low": 1778.0, "close": 1778.0, "open": 1780.0}
{"instrument_id": "j1805", "date_time": "20180413 23:25:01", "high": 1780.0, "low": 1778.0, "close": 1780.0, "open": 1778.0}
{"instrument_id": "j1805", "date_time": "20180413 23:26:00", "high": 1780.0, "low": 1779.0, "close": 1779.0, "open": 1780.0}
{"instrument_id": "j1805", "date_time": "20180413 23:27:01", "high": 1779.5, "low": 1778.0, "close": 1779.5, "open": 1778.0}
{"instrument_id": "j1805", "date_time": "20180413 23:28:01", "high": 1779.5, "low": 1778.0, "close": 1778.5, "open": 1779.5}
{"instrument_id": "j1805", "date_time": "20180413 23:29:01", "high": 1779.0, "low": 1778.0, "close": 1778.0, "open": 1778.5}
{"instrument_id": "j1805", "date_time": "20180413 21:22:01", "high": 1786.0, "low": 1785.0, "close": 1785.0, "open": 1785.0}
{"instrument_id": "j1805", "date_time": "20180413 21:23:00", "high": 1787.0, "low": 1785.0, "close": 1785.0, "open": 1785.0}
{"instrument_id": "j1805", "date_time": "20180413 21:24:00", "high": 1785.0, "low": 1784.0, "close": 1784.0, "open": 1785.0}
{"instrument_id": "j1805", "date_time": "20180413 21:25:01", "high": 1784.5, "low": 1782.0, "close": 1782.0, "open": 1784.5}
{"instrument_id": "j1805", "date_time": "20180413 21:26:00", "high": 1785.5, "low": 1781.5, "close": 1785.0, "open": 1782.0}
{"instrument_id": "j1805", "date_time": "20180413 21:27:02", "high": 1786.5, "low": 1784.0, "close": 1784.5, "open": 1785.0}
{"instrument_id": "j1805", "date_time": "20180413 21:28:02", "high": 1786.5, "low": 1782.5, "close": 1786.5, "open": 1784.5}
{"instrument_id": "j1805", "date_time": "20180413 21:29:00", "high": 1786.5, "low": 1782.0, "close": 1782.5, "open": 1786.5}
{"instrument_id": "j1805", "date_time": "20180413 21:30:00", "high": 1784.5, "low": 1781.0, "close": 1783.5, "open": 1782.5}
{"instrument_id": "j1805", "date_time": "20180413 21:31:00", "high": 1786.5, "low": 1783.5, "close": 1786.0, "open": 1783.5}
{"instrument_id": "j1805", "date_time": "20180413 21:32:00", "high": 1786.0, "low": 1784.0, "close": 1784.5, "open": 1786.0}
{"instrument_id": "j1805", "date_time": "20180413 21:33:02", "high": 1785.0, "low": 1783.0, "close": 1784.5, "open": 1784.0}
{"instrument_id": "j1805", "date_time": "20180413 21:34:00", "high": 1785.0, "low": 1783.5, "close": 1785.0, "open": 1784.5}
{"instrument_id": "j1805", "date_time": "20180413 21:36:04", "high": 1786.0, "low": 1784.5, "close": 1785.5, "open": 1784.5}
{"instrument_id": "j1805", "date_time": "20180413 21:37:02", "high": 1785.5, "low": 1783.5, "close": 1785.0, "open": 1785.5}
{"instrument_id": "j1805", "date_time": "20180413 21:38:07", "high": 1785.0, "low": 1783.0, "close": 1784.0, "open": 1785.0}
{"instrument_id": "j1805", "date_time": "20180413 21:39:00", "high": 1784.5, "low": 1783.0, "close": 1783.5, "open": 1784.0}
{"instrument_id": "j1805", "date_time": "20180413 21:40:03", "high": 1783.5, "low": 1782.5, "close": 1783.0, "open": 1783.0}
{"instrument_id": "j1805", "date_time": "20180413 21:41:00", "high": 1783.5, "low": 1782.5, "close": 1783.5, "open": 1782.5}
{"instrument_id": "j1805", "date_time": "20180413 21:42:05", "high": 1784.0, "low": 1782.5, "close": 1783.0, "open": 1783.5}
{"instrument_id": "j1805", "date_time": "20180413 21:43:00", "high": 1783.0, "low": 1781.0, "close": 1781.0, "open": 1782.5}
{"instrument_id": "j1805", "date_time": "20180413 21:44:02", "high": 1782.0, "low": 1781.0, "close": 1781.0, "open": 1781.0}
{"instrument_id": "j1805", "date_time": "20180413 21:45:01", "high": 1783.0, "low": 1781.0, "close": 1782.0, "open": 1781.0}
{"instrument_id": "j1805", "date_time": "20180413 21:46:00", "high": 1783.5, "low": 1782.0, "close": 1782.5, "open": 1782.0}
{"instrument_id": "j1805", "date_time": "20180413 21:47:06", "high": 1784.5, "low": 1782.5, "close": 1783.5, "open": 1783.5}
{"instrument_id": "j1805", "date_time": "20180413 21:48:02", "high": 1783.5, "low": 1783.0, "close": 1783.5, "open": 1783.5}
{"instrument_id": "j1805", "date_time": "20180413 21:49:01", "high": 1785.0, "low": 1783.0, "close": 1783.5, "open": 1784.0}
{"instrument_id": "j1805", "date_time": "20180413 21:50:00", "high": 1784.5, "low": 1783.0, "close": 1784.5, "open": 1783.0}
{"instrument_id": "j1805", "date_time": "20180413 21:51:00", "high": 1784.5, "low": 1782.5, "close": 1784.5, "open": 1784.5}
{"instrument_id": "j1805", "date_time": "20180413 21:52:00", "high": 1784.5, "low": 1783.5, "close": 1784.0, "open": 1784.5}
{"instrument_id": "j1805", "date_time": "20180413 21:53:01", "high": 1785.0, "low": 1784.0, "close": 1784.5, "open": 1784.0}
{"instrument_id": "j1805", "date_time": "20180413 21:54:02", "high": 1785.0, "low": 1784.5, "close": 1784.5, "open": 1784.5}
{"instrument_id": "j1805", "date_time": "20180413 21:55:04", "high": 1784.5, "low": 1784.0, "close": 1784.0, "open": 1784.5}
{"instrument_id": "j1805", "date_time": "20180413 21:56:05", "high": 1786.0, "low": 1784.0, "close": 1786.0, "open": 1784.0}
{"instrument_id": "j1805", "date_time": "20180413 21:57:05", "high": 1786.0, "low": 1783.0, "close": 1783.5, "open": 1786.0}
{"instrument_id": "j1805", "date_time": "20180413 21:58:00", "high": 1784.0, "low": 1783.0, "close": 1784.0, "open": 1783.5}
{"instrument_id": "j1805", "date_time": "20180413 21:59:00", "high": 1784.5, "low": 1783.5, "close": 1784.0, "open": 1784.0}
{"instrument_id": "j1805", "date_time": "20180413 22:00:01", "high": 1784.5, "low": 1783.0, "close": 1784.5, "open": 1783.5}
{"instrument_id": "j1805", "date_time": "20180413 22:01:00", "high": 1785.0, "low": 1784.5, "close": 1785.0, "open": 1784.5}
{"instrument_id": "j1805", "date_time": "20180413 22:02:00", "high": 1785.5, "low": 1784.5, "close": 1784.5, "open": 1785.0}
{"instrument_id": "j1805", "date_time": "20180413 22:03:01", "high": 1784.5, "low": 1784.0, "close": 1784.0, "open": 1784.5}
{"instrument_id": "j1805", "date_time": "20180413 22:04:06", "high": 1784.5, "low": 1784.0, "close": 1784.0, "open": 1784.0}
{"instrument_id": "j1805", "date_time": "20180413 22:05:16", "high": 1784.0, "low": 1784.0, "close": 1784.0, "open": 1784.0}
{"instrument_id": "j1805", "date_time": "20180413 22:06:00", "high": 1785.0, "low": 1784.0, "close": 1784.0, "open": 1784.0}
{"instrument_id": "j1805", "date_time": "20180413 22:07:02", "high": 1785.0, "low": 1784.0, "close": 1784.5, "open": 1784.0}
{"instrument_id": "j1805", "date_time": "20180413 22:08:00", "high": 1787.5, "low": 1784.5, "close": 1786.0, "open": 1784.5}
{"instrument_id": "j1805", "date_time": "20180413 22:09:00", "high": 1787.5, "low": 1786.0, "close": 1786.5, "open": 1786.5}
{"instrument_id": "j1805", "date_time": "20180413 22:10:00", "high": 1786.5, "low": 1785.5, "close": 1785.5, "open": 1786.5}
{"instrument_id": "j1805", "date_time": "20180413 22:11:08", "high": 1786.0, "low": 1785.5, "close": 1785.5, "open": 1785.5}
{"instrument_id": "j1805", "date_time": "20180413 22:12:07", "high": 1786.5, "low": 1785.5, "close": 1786.5, "open": 1785.5}
{"instrument_id": "j1805", "date_time": "20180413 22:13:02", "high": 1786.5, "low": 1785.5, "close": 1785.5, "open": 1786.5}
{"instrument_id": "j1805", "date_time": "20180413 22:14:04", "high": 1786.0, "low": 1784.5, "close": 1785.0, "open": 1784.5}
{"instrument_id": "j1805", "date_time": "20180413 22:15:00", "high": 1785.0, "low": 1784.0, "close": 1785.0, "open": 1785.0}
{"instrument_id": "j1805", "date_time": "20180413 22:16:00", "high": 1787.0, "low": 1785.0, "close": 1786.0, "open": 1785.0}
{"instrument_id": "j1805", "date_time": "20180413 22:17:00", "high": 1786.0, "low": 1785.0, "close": 1785.5, "open": 1786.0}
{"instrument_id": "j1805", "date_time": "20180413 22:18:00", "high": 1786.0, "low": 1785.0, "close": 1786.0, "open": 1785.5}
{"instrument_id": "j1805", "date_time": "20180413 22:19:00", "high": 1786.5, "low": 1785.0, "close": 1785.0, "open": 1786.0}
{"instrument_id": "j1805", "date_time": "20180413 22:20:00", "high": 1786.0, "low": 1785.0, "close": 1785.5, "open": 1785.0}
{"instrument_id": "j1805", "date_time": "20180413 22:21:00", "high": 1786.0, "low": 1785.5, "close": 1785.5, "open": 1785.5}
{"instrument_id": "j1805", "date_time": "20180413 22:22:07", "high": 1786.0, "low": 1785.5, "close": 1785.5, "open": 1785.5}
{"instrument_id": "j1805", "date_time": "20180413 22:23:01", "high": 1786.0, "low": 1784.0, "close": 1784.0, "open": 1785.5}
{"instrument_id": "j1805", "date_time": "20180413 22:24:01", "high": 1784.0, "low": 1782.5, "close": 1783.5, "open": 1784.0}
{"instrument_id": "j1805", "date_time": "20180413 22:25:00", "high": 1785.0, "low": 1783.0, "close": 1784.0, "open": 1783.5}
{"instrument_id": "j1805", "date_time": "20180413 23:30:00", "high": 1778.0, "low": 1778.0, "close": 1778.0, "open": 1778.0}
{"instrument_id": "j1805", "date_time": "20180413 22:25:00", "high": 1785.0, "low": 1778.0, "close": 1785.0, "open": 1783.5}
{"instrument_id": "j1805", "date_time": "20180413 22:26:01", "high": 1787.5, "low": 1784.5, "close": 1786.5, "open": 1785.0}
{"instrument_id": "j1805", "date_time": "20180413 22:27:00", "high": 1787.0, "low": 1785.0, "close": 1786.5, "open": 1786.5}
{"instrument_id": "j1805", "date_time": "20180413 22:28:00", "high": 1786.0, "low": 1784.0, "close": 1785.5, "open": 1786.0}
{"instrument_id": "j1805", "date_time": "20180413 22:29:06", "high": 1785.5, "low": 1784.0, "close": 1785.0, "open": 1785.5}
{"instrument_id": "j1805", "date_time": "20180413 22:30:00", "high": 1785.0, "low": 1783.5, "close": 1785.0, "open": 1785.0}
{"instrument_id": "j1805", "date_time": "20180413 22:31:01", "high": 1785.0, "low": 1784.0, "close": 1784.0, "open": 1785.0}
{"instrument_id": "j1805", "date_time": "20180413 22:32:00", "high": 1784.5, "low": 1784.0, "close": 1784.0, "open": 1784.0}
{"instrument_id": "j1805", "date_time": "20180413 22:33:00", "high": 1785.0, "low": 1784.0, "close": 1785.0, "open": 1784.0}
{"instrument_id": "j1805", "date_time": "20180413 22:34:00", "high": 1785.0, "low": 1784.0, "close": 1784.5, "open": 1785.0}
{"instrument_id": "j1805", "date_time": "20180413 22:35:02", "high": 1784.5, "low": 1784.0, "close": 1784.5, "open": 1784.5}
{"instrument_id": "j1805", "date_time": "20180413 22:36:02", "high": 1784.5, "low": 1783.5, "close": 1783.5, "open": 1784.5}
{"instrument_id": "j1805", "date_time": "20180413 22:37:00", "high": 1784.0, "low": 1783.0, "close": 1784.0, "open": 1783.5}
{"instrument_id": "j1805", "date_time": "20180413 22:38:01", "high": 1785.0, "low": 1784.0, "close": 1785.0, "open": 1784.0}
{"instrument_id": "j1805", "date_time": "20180413 22:39:00", "high": 1785.0, "low": 1785.0, "close": 1785.0, "open": 1785.0}
{"instrument_id": "j1805", "date_time": "20180413 22:40:04", "high": 1785.0, "low": 1783.5, "close": 1783.5, "open": 1785.0}
{"instrument_id": "j1805", "date_time": "20180413 22:41:00", "high": 1784.0, "low": 1783.5, "close": 1783.5, "open": 1783.5}
{"instrument_id": "j1805", "date_time": "20180413 22:42:08", "high": 1785.0, "low": 1783.5, "close": 1783.5, "open": 1783.5}
{"instrument_id": "j1805", "date_time": "20180413 22:43:14", "high": 1784.5, "low": 1783.5, "close": 1783.5, "open": 1784.5}
{"instrument_id": "j1805", "date_time": "20180413 22:44:02", "high": 1784.0, "low": 1782.0, "close": 1784.0, "open": 1783.5}
{"instrument_id": "j1805", "date_time": "20180413 22:45:00", "high": 1785.0, "low": 1783.5, "close": 1784.5, "open": 1784.0}
{"instrument_id": "j1805", "date_time": "20180413 22:46:03", "high": 1785.0, "low": 1784.0, "close": 1784.5, "open": 1784.0}
{"instrument_id": "j1805", "date_time": "20180413 22:47:02", "high": 1784.5, "low": 1784.5, "close": 1784.5, "open": 1784.5}
{"instrument_id": "j1805", "date_time": "20180413 22:48:05", "high": 1784.5, "low": 1784.5, "close": 1784.5, "open": 1784.5}
{"instrument_id": "j1805", "date_time": "20180413 22:49:04", "high": 1784.5, "low": 1783.5, "close": 1784.0, "open": 1784.5}
{"instrument_id": "j1805", "date_time": "20180413 22:50:00", "high": 1785.0, "low": 1784.0, "close": 1785.0, "open": 1784.0}
{"instrument_id": "j1805", "date_time": "20180413 22:51:02", "high": 1785.5, "low": 1784.5, "close": 1785.0, "open": 1784.5}
{"instrument_id": "j1805", "date_time": "20180413 22:52:02", "high": 1785.0, "low": 1783.5, "close": 1784.0, "open": 1784.5}
{"instrument_id": "j1805", "date_time": "20180413 22:53:02", "high": 1785.0, "low": 1784.0, "close": 1784.0, "open": 1784.0}
{"instrument_id": "j1805", "date_time": "20180413 22:54:00", "high": 1784.5, "low": 1784.0, "close": 1784.5, "open": 1784.0}
{"instrument_id": "j1805", "date_time": "20180413 22:55:01", "high": 1784.5, "low": 1784.0, "close": 1784.5, "open": 1784.5}
{"instrument_id": "j1805", "date_time": "20180413 22:56:02", "high": 1784.5, "low": 1784.5, "close": 1784.5, "open": 1784.5}
{"instrument_id": "j1805", "date_time": "20180413 22:57:13", "high": 1784.5, "low": 1783.5, "close": 1783.5, "open": 1784.5}
{"instrument_id": "j1805", "date_time": "20180413 22:58:00", "high": 1784.0, "low": 1783.5, "close": 1784.0, "open": 1783.5}
{"instrument_id": "j1805", "date_time": "20180413 22:59:00", "high": 1784.0, "low": 1783.5, "close": 1783.5, "open": 1784.0}
{"instrument_id": "j1805", "date_time": "20180413 23:00:01", "high": 1784.5, "low": 1783.5, "close": 1784.0, "open": 1783.5}
{"instrument_id": "j1805", "date_time": "20180413 23:01:04", "high": 1784.0, "low": 1783.0, "close": 1783.0, "open": 1784.0}
{"instrument_id": "j1805", "date_time": "20180413 23:02:00", "high": 1783.5, "low": 1782.0, "close": 1782.5, "open": 1782.5}
{"instrument_id": "j1805", "date_time": "20180413 23:03:00", "high": 1783.5, "low": 1782.5, "close": 1782.5, "open": 1782.5}
{"instrument_id": "j1805", "date_time": "20180413 23:04:02", "high": 1783.5, "low": 1782.0, "close": 1782.0, "open": 1782.5}
{"instrument_id": "j1805", "date_time": "20180413 23:05:11", "high": 1783.5, "low": 1782.0, "close": 1783.5, "open": 1782.0}
{"instrument_id": "j1805", "date_time": "20180413 23:06:02", "high": 1784.0, "low": 1783.0, "close": 1783.0, "open": 1783.5}
{"instrument_id": "j1805", "date_time": "20180413 23:07:02", "high": 1783.0, "low": 1782.5, "close": 1782.5, "open": 1783.0}
{"instrument_id": "j1805", "date_time": "20180413 23:08:04", "high": 1782.5, "low": 1782.0, "close": 1782.0, "open": 1782.5}
{"instrument_id": "j1805", "date_time": "20180413 23:09:01", "high": 1782.5, "low": 1782.5, "close": 1782.5, "open": 1782.5}
{"instrument_id": "j1805", "date_time": "20180413 23:10:00", "high": 1782.5, "low": 1780.5, "close": 1781.0, "open": 1782.5}
{"instrument_id": "j1805", "date_time": "20180413 23:11:00", "high": 1781.0, "low": 1777.0, "close": 1778.5, "open": 1781.0}
{"instrument_id": "j1805", "date_time": "20180413 23:12:03", "high": 1778.5, "low": 1776.5, "close": 1776.5, "open": 1778.5}
{"instrument_id": "j1805", "date_time": "20180413 23:13:00", "high": 1779.0, "low": 1776.5, "close": 1778.0, "open": 1776.5}
{"instrument_id": "j1805", "date_time": "20180413 23:14:01", "high": 1778.5, "low": 1777.5, "close": 1777.5, "open": 1778.0}
{"instrument_id": "j1805", "date_time": "20180413 23:15:04", "high": 1778.5, "low": 1776.0, "close": 1778.0, "open": 1777.5}
{"instrument_id": "j1805", "date_time": "20180413 23:16:04", "high": 1778.5, "low": 1777.5, "close": 1778.0, "open": 1778.0}
{"instrument_id": "j1805", "date_time": "20180413 23:17:00", "high": 1778.0, "low": 1776.0, "close": 1776.0, "open": 1778.0}
{"instrument_id": "j1805", "date_time": "20180413 23:18:00", "high": 1781.0, "low": 1776.0, "close": 1778.0, "open": 1776.5}
{"instrument_id": "j1805", "date_time": "20180413 23:19:00", "high": 1778.0, "low": 1776.5, "close": 1777.5, "open": 1778.0}
{"instrument_id": "j1805", "date_time": "20180413 23:20:00", "high": 1778.0, "low": 1777.0, "close": 1778.0, "open": 1777.5}
{"instrument_id": "j1805", "date_time": "20180413 23:21:02", "high": 1778.5, "low": 1778.0, "close": 1778.5, "open": 1778.0}
{"instrument_id": "j1805", "date_time": "20180413 23:22:00", "high": 1778.5, "low": 1777.5, "close": 1778.0, "open": 1778.0}
{"instrument_id": "j1805", "date_time": "20180413 23:23:08", "high": 1780.0, "low": 1778.0, "close": 1779.0, "open": 1778.0}
{"instrument_id": "j1805", "date_time": "20180413 23:24:05", "high": 1780.0, "low": 1778.0, "close": 1778.0, "open": 1780.0}
{"instrument_id": "j1805", "date_time": "20180413 23:25:01", "high": 1780.0, "low": 1778.0, "close": 1780.0, "open": 1778.0}
{"instrument_id": "j1805", "date_time": "20180413 23:26:00", "high": 1780.0, "low": 1779.0, "close": 1779.0, "open": 1780.0}
{"instrument_id": "j1805", "date_time": "20180413 23:27:01", "high": 1779.5, "low": 1778.0, "close": 1779.5, "open": 1778.0}
{"instrument_id": "j1805", "date_time": "20180413 23:28:01", "high": 1779.5, "low": 1778.0, "close": 1778.5, "open": 1779.5}
{"instrument_id": "j1805", "date_time": "20180413 23:29:01", "high": 1779.0, "low": 1778.0, "close": 1778.0, "open": 1778.5}
{"instrument_id": "j1805", "date_time": "20180413 09:00:00", "high": 1782.5, "low": 1778.0, "close": 1780.5, "open": 1778.0}
{"instrument_id": "j1805", "date_time": "20180413 09:01:00", "high": 1783.5, "low": 1780.0, "close": 1782.5, "open": 1780.5}
{"instrument_id": "j1805", "date_time": "20180413 09:02:00", "high": 1784.0, "low": 1781.5, "close": 1783.5, "open": 1782.5}
{"instrument_id": "j1805", "date_time": "20180413 09:03:00", "high": 1783.5, "low": 1781.0, "close": 1781.0, "open": 1783.5}
{"instrument_id": "j1805", "date_time": "20180413 09:04:02", "high": 1783.5, "low": 1781.5, "close": 1782.5, "open": 1782.0}
{"instrument_id": "j1805", "date_time": "20180413 09:05:01", "high": 1784.5, "low": 1782.5, "close": 1783.0, "open": 1783.0}
{"instrument_id": "j1805", "date_time": "20180413 09:06:00", "high": 1784.5, "low": 1782.5, "close": 1784.0, "open": 1783.0}
{"instrument_id": "j1805", "date_time": "20180413 09:07:02", "high": 1787.0, "low": 1784.0, "close": 1786.5, "open": 1784.0}
{"instrument_id": "j1805", "date_time": "20180413 09:08:00", "high": 1787.5, "low": 1784.5, "close": 1786.0, "open": 1786.5}
{"instrument_id": "j1805", "date_time": "20180413 09:09:00", "high": 1786.0, "low": 1784.5, "close": 1785.5, "open": 1786.0}
{"instrument_id": "j1805", "date_time": "20180413 09:10:01", "high": 1787.0, "low": 1785.5, "close": 1786.0, "open": 1785.5}
{"instrument_id": "j1805", "date_time": "20180413 09:11:04", "high": 1789.0, "low": 1786.0, "close": 1788.5, "open": 1786.0}
{"instrument_id": "j1805", "date_time": "20180413 09:12:00", "high": 1789.0, "low": 1787.5, "close": 1788.0, "open": 1788.5}
{"instrument_id": "j1805", "date_time": "20180413 09:13:00", "high": 1788.0, "low": 1786.5, "close": 1786.5, "open": 1788.0}
{"instrument_id": "j1805", "date_time": "20180413 09:14:02", "high": 1788.0, "low": 1786.0, "close": 1787.5, "open": 1787.0}
{"instrument_id": "j1805", "date_time": "20180413 09:15:00", "high": 1787.5, "low": 1786.0, "close": 1786.0, "open": 1787.5}
{"instrument_id": "j1805", "date_time": "20180413 09:16:05", "high": 1787.5, "low": 1786.0, "close": 1787.0, "open": 1786.0}
{"instrument_id": "j1805", "date_time": "20180413 09:17:00", "high": 1788.0, "low": 1786.0, "close": 1787.0, "open": 1787.0}
{"instrument_id": "j1805", "date_time": "20180413 09:18:00", "high": 1788.5, "low": 1787.0, "close": 1788.5, "open": 1787.0}
{"instrument_id": "j1805", "date_time": "20180413 09:19:00", "high": 1790.0, "low": 1788.0, "close": 1790.0, "open": 1788.5}
{"instrument_id": "j1805", "date_time": "20180413 09:20:00", "high": 1790.0, "low": 1788.5, "close": 1789.5, "open": 1790.0}
{"instrument_id": "j1805", "date_time": "20180413 09:21:00", "high": 1790.0, "low": 1788.5, "close": 1790.0, "open": 1789.5}
{"instrument_id": "j1805", "date_time": "20180413 09:22:00", "high": 1790.5, "low": 1789.5, "close": 1790.5, "open": 1789.5}
{"instrument_id": "j1805", "date_time": "20180413 09:23:00", "high": 1791.0, "low": 1789.5, "close": 1789.5, "open": 1790.5}
{"instrument_id": "j1805", "date_time": "20180413 09:24:00", "high": 1791.0, "low": 1789.5, "close": 1791.0, "open": 1790.0}
{"instrument_id": "j1805", "date_time": "20180413 09:25:01", "high": 1791.0, "low": 1789.5, "close": 1789.5, "open": 1791.0}
{"instrument_id": "j1805", "date_time": "20180413 09:26:02", "high": 1790.5, "low": 1789.5, "close": 1790.0, "open": 1789.5}
{"instrument_id": "j1805", "date_time": "20180413 09:27:00", "high": 1790.0, "low": 1787.5, "close": 1787.5, "open": 1789.5}
{"instrument_id": "j1805", "date_time": "20180413 09:28:00", "high": 1789.5, "low": 1787.5, "close": 1789.5, "open": 1787.5}
{"instrument_id": "j1805", "date_time": "20180413 09:29:00", "high": 1790.5, "low": 1789.5, "close": 1790.0, "open": 1789.5}
{"instrument_id": "j1805", "date_time": "20180413 09:30:00", "high": 1791.0, "low": 1790.0, "close": 1790.5, "open": 1790.0}
{"instrument_id": "j1805", "date_time": "20180413 09:31:00", "high": 1792.0, "low": 1790.5, "close": 1791.0, "open": 1791.0}
{"instrument_id": "j1805", "date_time": "20180413 09:32:00", "high": 1792.0, "low": 1790.5, "close": 1792.0, "open": 1791.0}
{"instrument_id": "j1805", "date_time": "20180413 09:33:00", "high": 1795.0, "low": 1792.0, "close": 1795.0, "open": 1792.0}
{"instrument_id": "j1805", "date_time": "20180413 09:34:00", "high": 1795.0, "low": 1793.5, "close": 1794.5, "open": 1794.5}
{"instrument_id": "j1805", "date_time": "20180413 09:35:00", "high": 1796.5, "low": 1794.5, "close": 1796.5, "open": 1794.5}
{"instrument_id": "j1805", "date_time": "20180413 09:36:00", "high": 1797.0, "low": 1795.0, "close": 1795.0, "open": 1796.5}
{"instrument_id": "j1805", "date_time": "20180413 09:37:01", "high": 1796.5, "low": 1794.0, "close": 1795.0, "open": 1795.0}
{"instrument_id": "j1805", "date_time": "20180413 09:38:03", "high": 1795.0, "low": 1791.5, "close": 1791.5, "open": 1794.5}
{"instrument_id": "j1805", "date_time": "20180413 09:39:01", "high": 1792.0, "low": 1790.0, "close": 1791.0, "open": 1791.5}
{"instrument_id": "j1805", "date_time": "20180413 09:40:00", "high": 1793.0, "low": 1791.0, "close": 1792.5, "open": 1791.0}
{"instrument_id": "j1805", "date_time": "20180413 09:41:00", "high": 1792.5, "low": 1790.0, "close": 1792.5, "open": 1792.5}
{"instrument_id": "j1805", "date_time": "20180413 09:42:00", "high": 1792.5, "low": 1791.0, "close": 1792.0, "open": 1791.5}
{"instrument_id": "j1805", "date_time": "20180413 09:43:00", "high": 1792.5, "low": 1790.5, "close": 1790.5, "open": 1792.0}
{"instrument_id": "j1805", "date_time": "20180413 09:44:01", "high": 1792.0, "low": 1791.0, "close": 1791.0, "open": 1791.0}
{"instrument_id": "j1805", "date_time": "20180413 09:45:00", "high": 1792.0, "low": 1789.0, "close": 1790.0, "open": 1791.0}
{"instrument_id": "j1805", "date_time": "20180413 09:46:00", "high": 1791.0, "low": 1789.0, "close": 1789.5, "open": 1790.0}
{"instrument_id": "j1805", "date_time": "20180413 09:47:01", "high": 1790.0, "low": 1787.0, "close": 1789.0, "open": 1789.5}
{"instrument_id": "j1805", "date_time": "20180413 09:48:01", "high": 1789.0, "low": 1787.5, "close": 1788.5, "open": 1789.0}
{"instrument_id": "j1805", "date_time": "20180413 09:49:00", "high": 1789.0, "low": 1788.0, "close": 1789.0, "open": 1788.5}
{"instrument_id": "j1805", "date_time": "20180413 09:50:00", "high": 1789.5, "low": 1788.0, "close": 1789.5, "open": 1789.0}
{"instrument_id": "j1805", "date_time": "20180413 09:51:00", "high": 1791.0, "low": 1789.5, "close": 1790.5, "open": 1790.0}
{"instrument_id": "j1805", "date_time": "20180413 09:52:00", "high": 1790.5, "low": 1788.5, "close": 1789.5, "open": 1790.5}
{"instrument_id": "j1805", "date_time": "20180413 09:53:01", "high": 1789.5, "low": 1789.0, "close": 1789.5, "open": 1789.5}
{"instrument_id": "j1805", "date_time": "20180413 09:54:01", "high": 1790.5, "low": 1789.0, "close": 1790.5, "open": 1789.5}
{"instrument_id": "j1805", "date_time": "20180413 09:55:00", "high": 1791.5, "low": 1790.5, "close": 1791.5, "open": 1790.5}
{"instrument_id": "j1805", "date_time": "20180413 09:56:06", "high": 1791.5, "low": 1791.0, "close": 1791.5, "open": 1791.5}
{"instrument_id": "j1805", "date_time": "20180413 09:57:00", "high": 1791.5, "low": 1790.0, "close": 1790.0, "open": 1791.5}
{"instrument_id": "j1805", "date_time": "20180413 09:58:03", "high": 1790.0, "low": 1789.0, "close": 1789.0, "open": 1790.0}
{"instrument_id": "j1805", "date_time": "20180413 09:59:01", "high": 1790.5, "low": 1789.0, "close": 1790.5, "open": 1789.0}
{"instrument_id": "j1805", "date_time": "20180413 10:00:00", "high": 1792.0, "low": 1790.0, "close": 1790.0, "open": 1790.5}
{"instrument_id": "j1805", "date_time": "20180413 10:01:00", "high": 1793.0, "low": 1788.5, "close": 1788.5, "open": 1790.0}
{"instrument_id": "j1805", "date_time": "20180413 10:02:00", "high": 1788.5, "low": 1787.0, "close": 1788.5, "open": 1788.5}
{"instrument_id": "j1805", "date_time": "20180413 10:03:08", "high": 1788.5, "low": 1787.0, "close": 1787.5, "open": 1788.5}
{"instrument_id": "j1805", "date_time": "20180413 10:04:01", "high": 1787.5, "low": 1786.5, "close": 1787.0, "open": 1787.5}
{"instrument_id": "j1805", "date_time": "20180413 10:05:00", "high": 1789.0, "low": 1787.0, "close": 1789.0, "open": 1787.0}
{"instrument_id": "j1805", "date_time": "20180413 10:06:01", "high": 1789.0, "low": 1787.0, "close": 1787.0, "open": 1789.0}
{"instrument_id": "j1805", "date_time": "20180413 10:07:00", "high": 1788.5, "low": 1786.5, "close": 1787.0, "open": 1787.0}
{"instrument_id": "j1805", "date_time": "20180413 10:08:02", "high": 1787.0, "low": 1786.0, "close": 1786.0, "open": 1787.0}
{"instrument_id": "j1805", "date_time": "20180413 10:09:00", "high": 1788.0, "low": 1785.5, "close": 1786.0, "open": 1785.5}
{"instrument_id": "j1805", "date_time": "20180413 10:10:01", "high": 1790.0, "low": 1786.5, "close": 1790.0, "open": 1786.5}
{"instrument_id": "j1805", "date_time": "20180413 10:11:00", "high": 1790.0, "low": 1787.0, "close": 1788.5, "open": 1790.0}
{"instrument_id": "j1805", "date_time": "20180413 10:12:02", "high": 1788.5, "low": 1786.5, "close": 1787.0, "open": 1788.5}
{"instrument_id": "j1805", "date_time": "20180413 10:13:00", "high": 1788.5, "low": 1786.5, "close": 1786.5, "open": 1787.0}
{"instrument_id": "j1805", "date_time": "20180413 10:14:02", "high": 1787.5, "low": 1783.5, "close": 1784.5, "open": 1786.5}
{"instrument_id": "j1805", "date_time": "20180413 10:30:00", "high": 1786.5, "low": 1784.0, "close": 1786.0, "open": 1784.0}
{"instrument_id": "j1805", "date_time": "20180413 10:31:01", "high": 1786.0, "low": 1783.5, "close": 1784.5, "open": 1786.0}
{"instrument_id": "j1805", "date_time": "20180413 10:32:04", "high": 1785.5, "low": 1783.5, "close": 1784.0, "open": 1783.5}
{"instrument_id": "j1805", "date_time": "20180413 10:33:01", "high": 1785.0, "low": 1784.0, "close": 1785.0, "open": 1784.0}
{"instrument_id": "j1805", "date_time": "20180413 10:34:02", "high": 1785.0, "low": 1783.0, "close": 1783.0, "open": 1785.0}
{"instrument_id": "j1805", "date_time": "20180413 10:35:00", "high": 1785.0, "low": 1783.0, "close": 1783.5, "open": 1784.0}
{"instrument_id": "j1805", "date_time": "20180413 10:36:00", "high": 1783.5, "low": 1782.0, "close": 1782.0, "open": 1783.5}
{"instrument_id": "j1805", "date_time": "20180413 10:37:03", "high": 1783.5, "low": 1781.5, "close": 1783.5, "open": 1782.0}
{"instrument_id": "j1805", "date_time": "20180413 10:38:00", "high": 1783.5, "low": 1781.5, "close": 1783.5, "open": 1783.5}
{"instrument_id": "j1805", "date_time": "20180413 10:39:00", "high": 1784.0, "low": 1783.0, "close": 1783.5, "open": 1783.5}
{"instrument_id": "j1805", "date_time": "20180413 10:40:00", "high": 1783.5, "low": 1782.5, "close": 1783.5, "open": 1783.0}
{"instrument_id": "j1805", "date_time": "20180413 10:41:00", "high": 1785.0, "low": 1783.5, "close": 1785.0, "open": 1783.5}
{"instrument_id": "j1805", "date_time": "20180413 10:42:00", "high": 1785.0, "low": 1784.0, "close": 1784.0, "open": 1785.0}
{"instrument_id": "j1805", "date_time": "20180413 10:43:00", "high": 1785.5, "low": 1783.5, "close": 1785.5, "open": 1784.0}
{"instrument_id": "j1805", "date_time": "20180413 10:44:03", "high": 1786.5, "low": 1785.0, "close": 1786.5, "open": 1785.0}
{"instrument_id": "j1805", "date_time": "20180413 10:45:05", "high": 1786.5, "low": 1784.5, "close": 1785.0, "open": 1786.5}
{"instrument_id": "j1805", "date_time": "20180413 10:46:02", "high": 1785.5, "low": 1784.5, "close": 1785.5, "open": 1785.0}
{"instrument_id": "j1805", "date_time": "20180413 10:47:02", "high": 1785.5, "low": 1784.5, "close": 1785.0, "open": 1785.5}
{"instrument_id": "j1805", "date_time": "20180413 10:48:05", "high": 1786.0, "low": 1785.0, "close": 1786.0, "open": 1785.0}
{"instrument_id": "j1805", "date_time": "20180413 10:49:01", "high": 1787.0, "low": 1785.5, "close": 1786.5, "open": 1786.0}
{"instrument_id": "j1805", "date_time": "20180413 10:50:01", "high": 1786.5, "low": 1786.5, "close": 1786.5, "open": 1786.5}
{"instrument_id": "j1805", "date_time": "20180413 10:51:06", "high": 1786.5, "low": 1785.5, "close": 1785.5, "open": 1786.5}
{"instrument_id": "j1805", "date_time": "20180413 10:52:00", "high": 1786.0, "low": 1785.0, "close": 1785.0, "open": 1785.5}
{"instrument_id": "j1805", "date_time": "20180413 10:53:04", "high": 1786.5, "low": 1785.5, "close": 1785.5, "open": 1786.0}
{"instrument_id": "j1805", "date_time": "20180413 10:54:00", "high": 1786.5, "low": 1785.5, "close": 1785.5, "open": 1785.5}
{"instrument_id": "j1805", "date_time": "20180413 10:55:00", "high": 1786.0, "low": 1785.0, "close": 1786.0, "open": 1785.0}
{"instrument_id": "j1805", "date_time": "20180413 10:56:00", "high": 1786.5, "low": 1786.0, "close": 1786.5, "open": 1786.0}
{"instrument_id": "j1805", "date_time": "20180413 10:57:06", "high": 1787.0, "low": 1786.5, "close": 1786.5, "open": 1787.0}
{"instrument_id": "j1805", "date_time": "20180413 10:58:00", "high": 1786.5, "low": 1786.5, "close": 1786.5, "open": 1786.5}
{"instrument_id": "j1805", "date_time": "20180413 10:59:12", "high": 1786.5, "low": 1785.0, "close": 1785.0, "open": 1786.5}
{"instrument_id": "j1805", "date_time": "20180413 11:00:02", "high": 1786.5, "low": 1785.0, "close": 1786.0, "open": 1785.0}
{"instrument_id": "j1805", "date_time": "20180413 11:01:06", "high": 1785.5, "low": 1785.5, "close": 1785.5, "open": 1785.5}
{"instrument_id": "j1805", "date_time": "20180413 11:02:00", "high": 1785.5, "low": 1784.5, "close": 1785.0, "open": 1785.5}
{"instrument_id": "j1805", "date_time": "20180413 11:03:02", "high": 1787.5, "low": 1784.5, "close": 1787.0, "open": 1785.0}
{"instrument_id": "j1805", "date_time": "20180413 11:04:00", "high": 1788.0, "low": 1786.0, "close": 1787.5, "open": 1787.0}
{"instrument_id": "j1805", "date_time": "20180413 11:05:00", "high": 1788.5, "low": 1786.5, "close": 1788.5, "open": 1788.0}
{"instrument_id": "j1805", "date_time": "20180413 11:06:01", "high": 1788.5, "low": 1786.5, "close": 1787.5, "open": 1788.5}
{"instrument_id": "j1805", "date_time": "20180413 11:07:01", "high": 1787.5, "low": 1787.0, "close": 1787.5, "open": 1787.5}
{"instrument_id": "j1805", "date_time": "20180413 11:08:00", "high": 1788.5, "low": 1786.0, "close": 1786.5, "open": 1787.5}
{"instrument_id": "j1805", "date_time": "20180413 11:09:01", "high": 1786.5, "low": 1785.5, "close": 1786.5, "open": 1786.5}
{"instrument_id": "j1805", "date_time": "20180413 11:10:00", "high": 1788.0, "low": 1786.0, "close": 1787.5, "open": 1786.0}
{"instrument_id": "j1805", "date_time": "20180413 11:11:03", "high": 1788.5, "low": 1787.0, "close": 1787.5, "open": 1787.5}
{"instrument_id": "j1805", "date_time": "20180413 11:12:01", "high": 1789.5, "low": 1788.0, "close": 1789.0, "open": 1788.0}
{"instrument_id": "j1805", "date_time": "20180413 11:13:00", "high": 1791.0, "low": 1788.5, "close": 1788.5, "open": 1789.0}
{"instrument_id": "j1805", "date_time": "20180413 11:14:02", "high": 1789.5, "low": 1788.0, "close": 1788.5, "open": 1788.5}
{"instrument_id": "j1805", "date_time": "20180413 11:15:00", "high": 1790.5, "low": 1788.5, "close": 1789.5, "open": 1788.5}
{"instrument_id": "j1805", "date_time": "20180413 11:16:01", "high": 1790.5, "low": 1789.5, "close": 1790.0, "open": 1789.5}
{"instrument_id": "j1805", "date_time": "20180413 11:17:02", "high": 1790.5, "low": 1790.0, "close": 1790.5, "open": 1790.0}
{"instrument_id": "j1805", "date_time": "20180413 11:18:08", "high": 1790.5, "low": 1788.5, "close": 1790.0, "open": 1790.5}
{"instrument_id": "j1805", "date_time": "20180413 11:19:03", "high": 1790.5, "low": 1789.0, "close": 1789.5, "open": 1790.0}
{"instrument_id": "j1805", "date_time": "20180413 11:20:01", "high": 1790.0, "low": 1789.5, "close": 1789.5, "open": 1789.5}
{"instrument_id": "j1805", "date_time": "20180413 11:21:02", "high": 1790.0, "low": 1789.0, "close": 1789.5, "open": 1789.5}
{"instrument_id": "j1805", "date_time": "20180413 11:22:00", "high": 1790.0, "low": 1789.5, "close": 1789.5, "open": 1789.5}
{"instrument_id": "j1805", "date_time": "20180413 11:23:07", "high": 1791.5, "low": 1789.5, "close": 1791.0, "open": 1790.0}
{"instrument_id": "j1805", "date_time": "20180413 11:24:00", "high": 1791.5, "low": 1791.0, "close": 1791.0, "open": 1791.0}
{"instrument_id": "j1805", "date_time": "20180413 11:25:01", "high": 1792.5, "low": 1791.0, "close": 1791.0, "open": 1791.0}
{"instrument_id": "j1805", "date_time": "20180413 11:26:10", "high": 1791.0, "low": 1789.0, "close": 1789.5, "open": 1791.0}
{"instrument_id": "j1805", "date_time": "20180413 11:27:03", "high": 1790.5, "low": 1788.5, "close": 1790.0, "open": 1789.5}
{"instrument_id": "j1805", "date_time": "20180413 11:28:00", "high": 1790.5, "low": 1789.0, "close": 1789.0, "open": 1789.5}
{"instrument_id": "j1805", "date_time": "20180413 11:29:04", "high": 1791.5, "low": 1789.0, "close": 1791.5, "open": 1789.0}
{"instrument_id": "j1805", "date_time": "20180413 13:30:00", "high": 1794.5, "low": 1791.0, "close": 1792.0, "open": 1791.0}
{"instrument_id": "j1805", "date_time": "20180413 13:31:00", "high": 1796.0, "low": 1792.5, "close": 1795.0, "open": 1792.5}
{"instrument_id": "j1805", "date_time": "20180413 13:32:00", "high": 1795.5, "low": 1793.0, "close": 1794.5, "open": 1795.0}
{"instrument_id": "j1805", "date_time": "20180413 13:33:00", "high": 1795.5, "low": 1794.0, "close": 1794.0, "open": 1794.5}
{"instrument_id": "j1805", "date_time": "20180413 13:34:00", "high": 1794.5, "low": 1791.0, "close": 1794.0, "open": 1794.0}
{"instrument_id": "j1805", "date_time": "20180413 13:35:02", "high": 1795.5, "low": 1792.5, "close": 1792.5, "open": 1794.0}
{"instrument_id": "j1805", "date_time": "20180413 13:36:00", "high": 1793.5, "low": 1790.5, "close": 1790.5, "open": 1792.5}
{"instrument_id": "j1805", "date_time": "20180413 13:37:01", "high": 1794.0, "low": 1790.5, "close": 1793.5, "open": 1791.0}
{"instrument_id": "j1805", "date_time": "20180413 13:38:00", "high": 1795.5, "low": 1793.5, "close": 1794.5, "open": 1793.5}
{"instrument_id": "j1805", "date_time": "20180413 13:39:00", "high": 1795.0, "low": 1791.5, "close": 1793.5, "open": 1794.5}
{"instrument_id": "j1805", "date_time": "20180413 13:40:00", "high": 1795.5, "low": 1792.0, "close": 1793.5, "open": 1793.5}
{"instrument_id": "j1805", "date_time": "20180413 13:41:00", "high": 1795.0, "low": 1792.5, "close": 1794.0, "open": 1793.5}
{"instrument_id": "j1805", "date_time": "20180413 13:42:00", "high": 1796.0, "low": 1792.0, "close": 1792.0, "open": 1794.5}
{"instrument_id": "j1805", "date_time": "20180413 13:43:00", "high": 1794.5, "low": 1791.0, "close": 1791.0, "open": 1794.5}
{"instrument_id": "j1805", "date_time": "20180413 13:44:02", "high": 1791.0, "low": 1789.0, "close": 1789.0, "open": 1791.0}
{"instrument_id": "j1805", "date_time": "20180413 13:45:00", "high": 1791.0, "low": 1787.5, "close": 1789.0, "open": 1789.0}
{"instrument_id": "j1805", "date_time": "20180413 13:46:00", "high": 1790.0, "low": 1787.5, "close": 1787.5, "open": 1789.0}
{"instrument_id": "j1805", "date_time": "20180413 13:47:02", "high": 1788.5, "low": 1787.0, "close": 1788.0, "open": 1788.0}
{"instrument_id": "j1805", "date_time": "20180413 13:48:00", "high": 1788.0, "low": 1786.5, "close": 1787.0, "open": 1788.0}
{"instrument_id": "j1805", "date_time": "20180413 13:49:00", "high": 1789.5, "low": 1787.0, "close": 1789.0, "open": 1787.0}
{"instrument_id": "j1805", "date_time": "20180413 13:50:00", "high": 1790.0, "low": 1789.0, "close": 1789.5, "open": 1789.0}
{"instrument_id": "j1805", "date_time": "20180413 13:51:00", "high": 1789.5, "low": 1788.0, "close": 1789.0, "open": 1789.5}
{"instrument_id": "j1805", "date_time": "20180413 13:52:00", "high": 1789.0, "low": 1787.5, "close": 1788.5, "open": 1789.0}
{"instrument_id": "j1805", "date_time": "20180413 13:53:05", "high": 1789.0, "low": 1787.5, "close": 1788.5, "open": 1788.5}
{"instrument_id": "j1805", "date_time": "20180413 13:54:00", "high": 1789.5, "low": 1788.5, "close": 1788.5, "open": 1788.5}
{"instrument_id": "j1805", "date_time": "20180413 13:55:00", "high": 1788.5, "low": 1786.5, "close": 1787.0, "open": 1788.5}
{"instrument_id": "j1805", "date_time": "20180413 13:56:00", "high": 1788.0, "low": 1787.0, "close": 1787.5, "open": 1787.0}
{"instrument_id": "j1805", "date_time": "20180413 13:57:01", "high": 1788.0, "low": 1786.5, "close": 1787.0, "open": 1787.5}
{"instrument_id": "j1805", "date_time": "20180413 13:58:00", "high": 1788.5, "low": 1787.0, "close": 1788.0, "open": 1787.0}
{"instrument_id": "j1805", "date_time": "20180413 13:59:00", "high": 1789.0, "low": 1788.0, "close": 1789.0, "open": 1788.0}
{"instrument_id": "j1805", "date_time": "20180413 14:00:00", "high": 1789.5, "low": 1788.5, "close": 1789.0, "open": 1789.0}
{"instrument_id": "j1805", "date_time": "20180413 14:01:00", "high": 1789.5, "low": 1788.5, "close": 1789.0, "open": 1789.0}
{"instrument_id": "j1805", "date_time": "20180413 14:02:00", "high": 1789.5, "low": 1788.5, "close": 1789.5, "open": 1788.5}
{"instrument_id": "j1805", "date_time": "20180413 14:03:02", "high": 1789.5, "low": 1788.0, "close": 1789.0, "open": 1788.0}
{"instrument_id": "j1805", "date_time": "20180413 14:04:03", "high": 1789.0, "low": 1788.0, "close": 1788.0, "open": 1789.0}
{"instrument_id": "j1805", "date_time": "20180413 14:05:00", "high": 1789.0, "low": 1787.5, "close": 1789.0, "open": 1788.0}
{"instrument_id": "j1805", "date_time": "20180413 14:06:00", "high": 1789.5, "low": 1788.0, "close": 1788.0, "open": 1789.0}
{"instrument_id": "j1805", "date_time": "20180413 14:07:01", "high": 1789.0, "low": 1788.0, "close": 1788.5, "open": 1788.0}
{"instrument_id": "j1805", "date_time": "20180413 14:08:04", "high": 1789.0, "low": 1788.5, "close": 1789.0, "open": 1788.5}
{"instrument_id": "j1805", "date_time": "20180413 14:09:03", "high": 1789.0, "low": 1787.5, "close": 1787.5, "open": 1789.0}
{"instrument_id": "j1805", "date_time": "20180413 14:10:01", "high": 1787.5, "low": 1787.0, "close": 1787.5, "open": 1787.0}
{"instrument_id": "j1805", "date_time": "20180413 14:11:02", "high": 1789.0, "low": 1788.5, "close": 1789.0, "open": 1788.5}
{"instrument_id": "j1805", "date_time": "20180413 14:12:01", "high": 1790.5, "low": 1788.5, "close": 1790.0, "open": 1789.0}
{"instrument_id": "j1805", "date_time": "20180413 14:13:00", "high": 1791.5, "low": 1790.0, "close": 1790.5, "open": 1790.0}
{"instrument_id": "j1805", "date_time": "20180413 14:14:00", "high": 1790.5, "low": 1789.5, "close": 1790.0, "open": 1790.5}
{"instrument_id": "j1805", "date_time": "20180413 14:15:00", "high": 1790.0, "low": 1788.5, "close": 1789.0, "open": 1790.0}
{"instrument_id": "j1805", "date_time": "20180413 14:16:03", "high": 1789.5, "low": 1789.0, "close": 1789.0, "open": 1789.0}
{"instrument_id": "j1805", "date_time": "20180413 14:17:03", "high": 1789.5, "low": 1788.0, "close": 1789.5, "open": 1789.0}
{"instrument_id": "j1805", "date_time": "20180413 14:18:00", "high": 1791.0, "low": 1789.5, "close": 1790.5, "open": 1789.5}
{"instrument_id": "j1805", "date_time": "20180413 14:19:00", "high": 1792.0, "low": 1790.5, "close": 1792.0, "open": 1790.5}
{"instrument_id": "j1805", "date_time": "20180413 14:20:00", "high": 1792.0, "low": 1790.0, "close": 1790.5, "open": 1792.0}
{"instrument_id": "j1805", "date_time": "20180413 14:21:01", "high": 1791.0, "low": 1789.5, "close": 1791.0, "open": 1790.5}
{"instrument_id": "j1805", "date_time": "20180413 14:22:08", "high": 1791.0, "low": 1790.5, "close": 1790.5, "open": 1791.0}
{"instrument_id": "j1805", "date_time": "20180413 14:23:01", "high": 1790.5, "low": 1790.5, "close": 1790.5, "open": 1790.5}
{"instrument_id": "j1805", "date_time": "20180413 14:24:00", "high": 1792.0, "low": 1790.5, "close": 1792.0, "open": 1790.5}
{"instrument_id": "j1805", "date_time": "20180413 14:25:00", "high": 1793.0, "low": 1791.0, "close": 1792.0, "open": 1792.0}
{"instrument_id": "j1805", "date_time": "20180413 14:26:00", "high": 1793.5, "low": 1791.0, "close": 1793.5, "open": 1792.0}
{"instrument_id": "j1805", "date_time": "20180413 14:27:00", "high": 1793.5, "low": 1792.0, "close": 1792.5, "open": 1793.5}
{"instrument_id": "j1805", "date_time": "20180413 14:28:02", "high": 1795.0, "low": 1792.0, "close": 1795.0, "open": 1792.5}
{"instrument_id": "j1805", "date_time": "20180413 14:29:00", "high": 1795.0, "low": 1792.0, "close": 1793.0, "open": 1795.0}
{"instrument_id": "j1805", "date_time": "20180413 14:30:00", "high": 1794.0, "low": 1792.0, "close": 1793.5, "open": 1793.0}
{"instrument_id": "j1805", "date_time": "20180413 14:31:00", "high": 1793.5, "low": 1792.5, "close": 1793.0, "open": 1793.5}
{"instrument_id": "j1805", "date_time": "20180413 14:32:00", "high": 1793.5, "low": 1792.0, "close": 1792.5, "open": 1793.5}
{"instrument_id": "j1805", "date_time": "20180413 14:33:00", "high": 1792.5, "low": 1791.5, "close": 1791.5, "open": 1792.5}
{"instrument_id": "j1805", "date_time": "20180413 14:34:00", "high": 1791.5, "low": 1790.0, "close": 1790.5, "open": 1791.5}
{"instrument_id": "j1805", "date_time": "20180413 14:35:01", "high": 1791.0, "low": 1789.5, "close": 1790.0, "open": 1791.0}
{"instrument_id": "j1805", "date_time": "20180413 14:36:00", "high": 1790.0, "low": 1788.0, "close": 1788.5, "open": 1790.0}
{"instrument_id": "j1805", "date_time": "20180413 14:37:01", "high": 1788.0, "low": 1786.0, "close": 1786.0, "open": 1787.5}
{"instrument_id": "j1805", "date_time": "20180413 14:38:00", "high": 1787.0, "low": 1785.5, "close": 1786.0, "open": 1786.0}
{"instrument_id": "j1805", "date_time": "20180413 14:39:00", "high": 1786.5, "low": 1784.5, "close": 1784.5, "open": 1786.0}
{"instrument_id": "j1805", "date_time": "20180413 14:40:00", "high": 1785.0, "low": 1780.5, "close": 1781.5, "open": 1784.5}
{"instrument_id": "j1805", "date_time": "20180413 14:41:00", "high": 1782.5, "low": 1780.0, "close": 1782.0, "open": 1780.5}
{"instrument_id": "j1805", "date_time": "20180413 14:42:00", "high": 1783.0, "low": 1782.0, "close": 1782.5, "open": 1782.0}
{"instrument_id": "j1805", "date_time": "20180413 14:43:00", "high": 1783.0, "low": 1781.0, "close": 1782.0, "open": 1782.0}
{"instrument_id": "j1805", "date_time": "20180413 14:44:01", "high": 1781.5, "low": 1780.0, "close": 1781.0, "open": 1781.5}
{"instrument_id": "j1805", "date_time": "20180413 14:45:01", "high": 1781.5, "low": 1780.0, "close": 1780.0, "open": 1781.0}
{"instrument_id": "j1805", "date_time": "20180413 14:46:00", "high": 1782.0, "low": 1780.0, "close": 1781.0, "open": 1780.0}
{"instrument_id": "j1805", "date_time": "20180413 14:47:00", "high": 1781.0, "low": 1780.0, "close": 1780.0, "open": 1781.0}
{"instrument_id": "j1805", "date_time": "20180413 14:48:00", "high": 1781.5, "low": 1778.5, "close": 1778.5, "open": 1780.0}
{"instrument_id": "j1805", "date_time": "20180413 14:49:00", "high": 1781.5, "low": 1778.0, "close": 1780.0, "open": 1778.5}
{"instrument_id": "j1805", "date_time": "20180413 14:50:00", "high": 1783.0, "low": 1778.5, "close": 1783.0, "open": 1780.0}
{"instrument_id": "j1805", "date_time": "20180413 14:51:00", "high": 1783.0, "low": 1781.0, "close": 1783.0, "open": 1783.0}
{"instrument_id": "j1805", "date_time": "20180413 14:52:01", "high": 1784.0, "low": 1782.0, "close": 1783.0, "open": 1782.5}
{"instrument_id": "j1805", "date_time": "20180413 14:53:04", "high": 1783.5, "low": 1782.0, "close": 1782.5, "open": 1783.0}
{"instrument_id": "j1805", "date_time": "20180413 14:54:03", "high": 1784.0, "low": 1782.0, "close": 1783.5, "open": 1782.5}
{"instrument_id": "j1805", "date_time": "20180413 14:55:00", "high": 1784.0, "low": 1782.0, "close": 1784.0, "open": 1782.5}
{"instrument_id": "j1805", "date_time": "20180413 14:56:00", "high": 1784.5, "low": 1783.0, "close": 1784.5, "open": 1784.0}
{"instrument_id": "j1805", "date_time": "20180413 14:57:00", "high": 1785.0, "low": 1783.0, "close": 1784.5, "open": 1784.5}
{"instrument_id": "j1805", "date_time": "20180413 14:58:00", "high": 1784.5, "low": 1783.5, "close": 1784.0, "open": 1784.5}
{"instrument_id": "j1805", "date_time": "20180413 14:59:02", "high": 1785.0, "low": 1782.5, "close": 1783.5, "open": 1783.0}
