{"instrument_id": "j1805", "date_time": "20180329 11:21:47", "high": 1768.5, "low": 1760.0, "close": 1763.5, "open": 1766.5}
{"instrument_id": "j1805", "date_time": "20180329 13:30:00", "high": 1777.5, "low": 1765.0, "close": 1766.5, "open": 1766.5}
{"instrument_id": "j1805", "date_time": "20180329 14:00:00", "high": 1774.0, "low": 1763.0, "close": 1766.5, "open": 1766.5}
{"instrument_id": "j1805", "date_time": "20180329 14:30:00", "high": 1786.0, "low": 1766.0, "close": 1778.5, "open": 1766.5}
{"instrument_id": "j1805", "date_time": "20180329 15:00:29", "high": 1778.5, "low": 1778.5, "close": 1778.5, "open": 1778.5}
