{"instrument_id": "rb1805", "date_time": "20180413 15:18:10", "high": 3715.0, "low": 3715.0, "close": 3715.0, "open": 3715.0}
{"instrument_id": "rb1805", "date_time": "20180416 18:33:13", "high": 3715.0, "low": 3715.0, "close": 3715.0, "open": 3715.0}
{"instrument_id": "rb1805", "date_time": "20180416 20:59:00", "high": 3714.0, "low": 3714.0, "close": 3714.0, "open": 3714.0}
{"instrument_id": "rb1805", "date_time": "20180416 21:00:00", "high": 3719.0, "low": 3709.0, "close": 3718.0, "open": 3714.0}
{"instrument_id": "rb1805", "date_time": "20180416 21:03:00", "high": 3719.000000000001, "low": 3714.0, "close": 3715.000000000001, "open": 3718.0}
{"instrument_id": "rb1805", "date_time": "20180416 21:06:00", "high": 3723.000000000001, "low": 3714.0, "close": 3722.000000000001, "open": 3715.000000000001}
{"instrument_id": "rb1805", "date_time": "20180416 21:09:00", "high": 3725.0, "low": 3716.0, "close": 3718.0, "open": 3723.000000000001}
{"instrument_id": "rb1805", "date_time": "20180416 21:12:00", "high": 3719.000000000001, "low": 3712.0, "close": 3716.0, "open": 3718.0}
{"instrument_id": "rb1805", "date_time": "20180416 21:15:00", "high": 3717.000000000001, "low": 3714.0, "close": 3716.0, "open": 3716.0}
{"instrument_id": "rb1805", "date_time": "20180416 21:18:00", "high": 3716.0, "low": 3712.0, "close": 3714.0, "open": 3716.0}
{"instrument_id": "rb1805", "date_time": "20180416 21:21:00", "high": 3717.000000000001, "low": 3714.0, "close": 3716.0, "open": 3714.0}
{"instrument_id": "rb1805", "date_time": "20180416 21:24:00", "high": 3717.0, "low": 3714.0, "close": 3716.0, "open": 3716.0}
{"instrument_id": "rb1805", "date_time": "20180416 21:27:01", "high": 3717.0, "low": 3713.0, "close": 3714.000000000001, "open": 3716.0}
{"instrument_id": "rb1805", "date_time": "20180416 21:30:00", "high": 3715.0, "low": 3712.0, "close": 3713.0, "open": 3714.000000000001}
{"instrument_id": "rb1805", "date_time": "20180416 21:33:00", "high": 3715.0, "low": 3712.0, "close": 3712.0, "open": 3714.0}
{"instrument_id": "rb1805", "date_time": "20180416 21:36:00", "high": 3715.0, "low": 3712.0, "close": 3715.0, "open": 3713.0}
{"instrument_id": "rb1805", "date_time": "20180416 21:39:00", "high": 3716.000000000001, "low": 3714.0, "close": 3715.000000000001, "open": 3715.0}
{"instrument_id": "rb1805", "date_time": "20180416 21:42:00", "high": 3715.0, "low": 3713.0, "close": 3713.0, "open": 3714.0}
{"instrument_id": "rb1805", "date_time": "20180416 21:45:01", "high": 3714.000000000001, "low": 3711.0, "close": 3712.0, "open": 3714.0}
{"instrument_id": "rb1805", "date_time": "20180416 21:48:00", "high": 3716.000000000001, "low": 3712.0, "close": 3714.0, "open": 3712.0}
{"instrument_id": "rb1805", "date_time": "20180416 21:51:00", "high": 3714.0, "low": 3712.000000000001, "close": 3714.0, "open": 3714.0}
{"instrument_id": "rb1805", "date_time": "20180416 21:54:00", "high": 3716.000000000001, "low": 3713.0, "close": 3716.000000000001, "open": 3714.0}
{"instrument_id": "rb1805", "date_time": "20180416 21:57:00", "high": 3715.0, "low": 3713.0, "close": 3714.0, "open": 3715.0}
{"instrument_id": "rb1805", "date_time": "20180416 22:00:00", "high": 3716.000000000001, "low": 3713.0, "close": 3715.0, "open": 3713.0}
{"instrument_id": "rb1805", "date_time": "20180416 22:03:00", "high": 3716.0, "low": 3713.0, "close": 3715.0, "open": 3715.0}
{"instrument_id": "rb1805", "date_time": "20180416 22:06:01", "high": 3715.0, "low": 3713.0, "close": 3713.0, "open": 3715.0}
{"instrument_id": "rb1805", "date_time": "20180416 22:09:00", "high": 3715.000000000001, "low": 3712.0, "close": 3712.0, "open": 3713.0}
{"instrument_id": "rb1805", "date_time": "20180416 22:12:00", "high": 3713.0, "low": 3710.0, "close": 3712.0, "open": 3712.0}
{"instrument_id": "rb1805", "date_time": "20180416 22:15:00", "high": 3717.0, "low": 3712.0, "close": 3713.0, "open": 3712.0}
{"instrument_id": "rb1805", "date_time": "20180416 22:18:00", "high": 3714.0, "low": 3712.0, "close": 3713.0, "open": 3713.0}
{"instrument_id": "rb1805", "date_time": "20180416 22:21:00", "high": 3714.0, "low": 3711.0, "close": 3712.0, "open": 3713.0}
{"instrument_id": "rb1805", "date_time": "20180416 22:24:00", "high": 3712.000000000001, "low": 3709.0, "close": 3710.0, "open": 3712.0}
{"instrument_id": "rb1805", "date_time": "20180416 22:27:00", "high": 3710.0, "low": 3705.0, "close": 3708.0, "open": 3710.0}
{"instrument_id": "rb1805", "date_time": "20180416 22:30:00", "high": 3712.000000000001, "low": 3707.0, "close": 3708.0, "open": 3708.0}
{"instrument_id": "rb1805", "date_time": "20180416 22:33:00", "high": 3711.0, "low": 3708.0, "close": 3710.0, "open": 3708.0}
{"instrument_id": "rb1805", "date_time": "20180416 22:36:00", "high": 3711.0, "low": 3709.0, "close": 3710.0, "open": 3710.0}
{"instrument_id": "rb1805", "date_time": "20180416 22:39:01", "high": 3711.0, "low": 3707.0, "close": 3709.0, "open": 3710.0}
{"instrument_id": "rb1805", "date_time": "20180416 22:42:01", "high": 3710.0, "low": 3708.000000000001, "close": 3709.0, "open": 3709.0}
{"instrument_id": "rb1805", "date_time": "20180416 22:45:00", "high": 3710.0000000000005, "low": 3709.0, "close": 3710.0, "open": 3709.0}
{"instrument_id": "rb1805", "date_time": "20180416 22:48:01", "high": 3712.0, "low": 3709.0, "close": 3711.0, "open": 3711.000000000001}
{"instrument_id": "rb1805", "date_time": "20180416 22:51:00", "high": 3711.0, "low": 3707.0, "close": 3709.0, "open": 3711.0}
{"instrument_id": "rb1805", "date_time": "20180416 22:54:00", "high": 3712.000000000001, "low": 3708.0, "close": 3710.0, "open": 3709.0}
{"instrument_id": "rb1805", "date_time": "20180416 22:57:00", "high": 3711.0, "low": 3705.0, "close": 3707.0, "open": 3710.0}
